setup.py
data_process_hupo/__init__.py
data_process_hupo.egg-info/PKG-INFO
data_process_hupo.egg-info/SOURCES.txt
data_process_hupo.egg-info/dependency_links.txt
data_process_hupo.egg-info/not-zip-safe
data_process_hupo.egg-info/top_level.txt