Metadata-Version: 1.0
Name: data-process-hupo
Version: 0.0.1
Summary: this is data process model
Home-page: UNKNOWN
Author: poge
Author-email: hupo4210@163.com
License: MIT
Platform: UNKNOWN
